bakalib/__init__.py
bakalib/utils.py
bakalib/core/__init__.py
bakalib/core/client.py
bakalib/extra/__init__.py
bakalib/extra/municipality.py
bakalib/modules/__init__.py
bakalib/modules/_generic.py
bakalib/modules/grades.py
bakalib/modules/timetable.py
bakalib-1.1.1.dist-info/LICENSE
bakalib-1.1.1.dist-info/METADATA
bakalib-1.1.1.dist-info/WHEEL
bakalib-1.1.1.dist-info/top_level.txt
bakalib-1.1.1.dist-info/RECORD
